effect_form_validators/__init__.py
effect_form_validators/apps.py
effect_form_validators/constants.py
effect_form_validators/effect_ae/__init__.py
effect_form_validators/effect_ae/death_report_form_validator.py
effect_form_validators/effect_consent/__init__.py
effect_form_validators/effect_consent/subject_consent_form_validator.py
effect_form_validators/effect_consent/subject_consent_update_v2_form_validator.py
effect_form_validators/effect_prn/__init__.py
effect_form_validators/effect_prn/hospitalization_form_validator.py
effect_form_validators/effect_reports/__init__.py
effect_form_validators/effect_reports/serum_crag_date_note_form_validator.py
effect_form_validators/effect_screening/__init__.py
effect_form_validators/effect_screening/subject_screening_form_validator.py
effect_form_validators/effect_subject/__init__.py
effect_form_validators/effect_subject/adherence/__init__.py
effect_form_validators/effect_subject/adherence/adherence_stage_four_form_validator.py
effect_form_validators/effect_subject/adherence/adherence_stage_one_form_validator.py
effect_form_validators/effect_subject/adherence/adherence_stage_three_form_validator.py
effect_form_validators/effect_subject/adherence/adherence_stage_two_form_validator.py
effect_form_validators/effect_subject/adherence/flucon_missed_doses_form_validator.py
effect_form_validators/effect_subject/adherence/flucyt_missed_doses_form_validator.py
effect_form_validators/effect_subject/adherence/missed_doses_form_validator_mixin.py
effect_form_validators/effect_subject/arv_history_form_validator.py
effect_form_validators/effect_subject/arv_treatment_form_validator.py
effect_form_validators/effect_subject/blood_culture_form_validator.py
effect_form_validators/effect_subject/chest_xray_form_validator.py
effect_form_validators/effect_subject/clinical_note_form_validator.py
effect_form_validators/effect_subject/diagnosis_form_validator.py
effect_form_validators/effect_subject/histopathology_form_validator.py
effect_form_validators-1.5.0.dist-info/licenses/LICENSE
effect_form_validators-1.5.0.dist-info/WHEEL
effect_form_validators-1.5.0.dist-info/METADATA
effect_form_validators-1.5.0.dist-info/RECORD
