Metadata-Version: 2.4
Name: effect-form-validators
Version: 1.5.0
Summary: Form validation classes for the EFFECT trial
Keywords: django,clinicedc,form validators,EFFECT EDC,EDC,clinical trials,META Trial,ISRCTN30579828
Author: Erik van Widenfelt, Jonathan Willitts
Author-email: Erik van Widenfelt <ew2789@gmail.com>, Jonathan Willitts <j.willitts@ucl.ac.uk>
License-Expression: GPL-3.0-or-later
License-File: LICENSE
Classifier: Development Status :: 5 - Production/Stable
Classifier: Framework :: Django
Classifier: Framework :: Django :: 5.2
Classifier: Intended Audience :: Developers
Classifier: Intended Audience :: Science/Research
Classifier: License :: OSI Approved :: GNU General Public License v3 (GPLv3)
Classifier: Operating System :: OS Independent
Classifier: Programming Language :: Python :: 3.12
Classifier: Programming Language :: Python :: 3.13
Requires-Dist: edc-csf>=1.3.0
Requires-Dist: edc-microbiology>=1.3.0
Requires-Python: >=3.12, <3.14
Project-URL: Changelog, https://github.com/effect-trial/effect-form-validators/blob/main/CHANGELOG
Project-URL: Homepage, https://github.com/effect-trial/effect-form-validators
Project-URL: Repository, https://github.com/effect-trial/effect-form-validators.git
